gitm/__init__.py
gitm/__main__.py
gitm/connection.py
gitm/db.py
gitm/pattern.py
gitm-1.0.1.dist-info/LICENSE
gitm-1.0.1.dist-info/METADATA
gitm-1.0.1.dist-info/WHEEL
gitm-1.0.1.dist-info/entry_points.txt
gitm-1.0.1.dist-info/top_level.txt
gitm-1.0.1.dist-info/RECORD
