Metadata-Version: 2.1
Name: gitm
Version: 1.0.1
Summary: Git emoji cli application
Author-email: AmirBahador Bahadori <amirbahador.pv@gmail.com>
License: Apache License
Project-URL: repository, https://github.com/amirbahador-hub/gitm
Keywords: gitm,Git emoji cli
Classifier: License :: OSI Approved :: Apache Software License
Classifier: Programming Language :: Python
Classifier: Programming Language :: Python :: 3
Requires-Python: >=3.10
License-File: LICENSE
Requires-Dist: typer (>=0.7.0)
Provides-Extra: build
Requires-Dist: build ; extra == 'build'
Requires-Dist: twine ; extra == 'build'
Requires-Dist: bumpver ; extra == 'build'
